asposestoragecloud/__init__.py
asposestoragecloud/api_client.py
asposestoragecloud/configuration.py
asposestoragecloud/rest.py
asposestoragecloud/apis/__init__.py
asposestoragecloud/apis/storage_api.py
asposestoragecloud/models/__init__.py
asposestoragecloud/models/access_token_response.py
asposestoragecloud/models/aspose_response.py
asposestoragecloud/models/copy_file_response.py
asposestoragecloud/models/create_folder_response.py
asposestoragecloud/models/disc_usage.py
asposestoragecloud/models/disc_usage_response.py
asposestoragecloud/models/file_exist.py
asposestoragecloud/models/file_exist_response.py
asposestoragecloud/models/file_response.py
asposestoragecloud/models/file_version.py
asposestoragecloud/models/file_versions_response.py
asposestoragecloud/models/files_response.py
asposestoragecloud/models/move_file_response.py
asposestoragecloud/models/move_folder_response.py
asposestoragecloud/models/remove_file_response.py
asposestoragecloud/models/remove_folder_response.py
asposestoragecloud/models/storage_exist_response.py
asposestoragecloud/models/upload_response.py
asposestoragecloud-1.0.6.dist-info/METADATA
asposestoragecloud-1.0.6.dist-info/RECORD
asposestoragecloud-1.0.6.dist-info/WHEEL
asposestoragecloud-1.0.6.dist-info/top_level.txt
test/__init__.py
test/test_storage_api.py
